pyLSPAPI.py
pyLSPAPI-1.0.4.dist-info/METADATA
pyLSPAPI-1.0.4.dist-info/WHEEL
pyLSPAPI-1.0.4.dist-info/top_level.txt
pyLSPAPI-1.0.4.dist-info/RECORD
