Metadata-Version: 2.1
Name: pyLSPAPI
Version: 1.0.4
Summary: Python API for Leitstellenspiel
Home-page: https://github.com/Leo-Aqua/LSPAPI
Author: Leo Aqua
Author-email: contact@leoaqua.de
Keywords: Leitstellenspiel,API,LSPAPI,LSS,API
Classifier: Programming Language :: Python :: 3
Classifier: License :: OSI Approved :: MIT License
Classifier: Operating System :: OS Independent
Requires-Python: >=3.6
Requires-Dist: pytest-playwright
Requires-Dist: requests
